[
    {
        "id": "/douga#目录",
        "title": "目录",
        "content": "目录"
    },
    {
        "id": "/douga#幻想万华镜",
        "title": "幻想万华镜",
        "content": "幻想万华镜"
    },
    {
        "id": "/douga#高清修复东方幻想万华镜全集",
        "title": "【高清修复】东方幻想万华镜全集",
        "content": "【高清修复】东方幻想万华镜全集"
    },
    {
        "id": "/douga#梦想夏乡",
        "title": "梦想夏乡",
        "content": "梦想夏乡"
    },
    {
        "id": "/douga#东方project梦想夏乡01",
        "title": "东方Project《梦想夏乡》01",
        "content": "东方Project《梦想夏乡》01"
    },
    {
        "id": "/douga#东方project梦想夏乡02",
        "title": "东方Project《梦想夏乡》02",
        "content": "东方Project《梦想夏乡》02"
    },
    {
        "id": "/douga#东方project梦想夏乡25",
        "title": "东方Project《梦想夏乡》2.5",
        "content": "东方Project《梦想夏乡》2.5"
    },
    {
        "id": "/douga#东方project梦想夏乡03",
        "title": "东方Project《梦想夏乡》03",
        "content": "东方Project《梦想夏乡》03"
    },
    {
        "id": "/douga#东方project梦想夏乡04",
        "title": "东方Project《梦想夏乡》04",
        "content": "东方Project《梦想夏乡》04"
    },
    {
        "id": "/douga#秘封活动记录",
        "title": "秘封活动记录",
        "content": "秘封活动记录"
    },
    {
        "id": "/douga#东方同人动画秘封活动记录1--月--高清全片",
        "title": "【东方同人动画】秘封活动记录1 -月- 高清全片",
        "content": "【东方同人动画】秘封活动记录1 -月- 高清全片"
    },
    {
        "id": "/douga#东方同人动画秘封活动记录2--祝--高清全片",
        "title": "【东方同人动画】秘封活动记录2 -祝- 高清全片",
        "content": "【东方同人动画】秘封活动记录2 -祝- 高清全片"
    },
    {
        "id": "/douga#东方同人动画秘封活动记录3--命运-上篇",
        "title": "【东方同人动画】秘封活动记录3 -命运-上篇",
        "content": "【东方同人动画】秘封活动记录3 -命运-上篇"
    },
    {
        "id": "/douga#东方无限螺旋",
        "title": "东方无限螺旋",
        "content": "东方无限螺旋"
    },
    {
        "id": "/douga#高清修复东方无限螺旋全26p",
        "title": "【高清修复】《东方无限螺旋》【全26P】",
        "content": "【高清修复】《东方无限螺旋》【全26P】"
    },
    {
        "id": "/douga#东方幼灵梦",
        "title": "东方幼灵梦",
        "content": "东方幼灵梦"
    },
    {
        "id": "/douga#东方东方幼灵梦-高清配音-重制版",
        "title": "【东方】东方幼灵梦 高清+配音 重制版",
        "content": "【东方】东方幼灵梦 高清+配音 重制版"
    },
    {
        "id": "/douga#东方灵灵梦",
        "title": "东方灵灵梦",
        "content": "东方灵灵梦"
    },
    {
        "id": "/douga#东方东方灵灵梦-高清配音",
        "title": "【东方】东方灵灵梦 高清+配音",
        "content": "【东方】东方灵灵梦 高清+配音"
    },
    {
        "id": "/douga#赛博东方酒家",
        "title": "赛博东方酒家",
        "content": "赛博东方酒家"
    },
    {
        "id": "/douga#赛博东方酒家第壹章-月曜日",
        "title": "「赛博东方酒家」·第壹章-月曜日",
        "content": "「赛博东方酒家」·第壹章-月曜日"
    },
    {
        "id": "/douga#赛博东方酒家第壹章-火曜日",
        "title": "「赛博东方酒家」·第壹章-火曜日",
        "content": "「赛博东方酒家」·第壹章-火曜日"
    },
    {
        "id": "/douga#赛博东方酒家第壹章-水曜日",
        "title": "「赛博东方酒家」·第壹章-水曜日",
        "content": "「赛博东方酒家」·第壹章-水曜日"
    },
    {
        "id": "/douga#赛博东方酒家第壹章-木曜日",
        "title": "「赛博东方酒家」·第壹章-木曜日",
        "content": "「赛博东方酒家」·第壹章-木曜日"
    },
    {
        "id": "/douga#minust",
        "title": "minusT",
        "content": "minusT"
    },
    {
        "id": "/douga#touhou-3d",
        "title": "Touhou 3D",
        "content": "Touhou 3D"
    },
    {
        "id": "/douga#原视频",
        "title": "原视频",
        "content": "原视频"
    },
    {
        "id": "/douga#touhou-3d-reimu-vs-remilia",
        "title": "[Touhou 3D] Reimu vs Remilia",
        "content": "[Touhou 3D] Reimu vs Remilia"
    },
    {
        "id": "/douga#touhou-3d-marisa-vs-flandre",
        "title": "[Touhou 3D] Marisa vs Flandre",
        "content": "[Touhou 3D] Marisa vs Flandre"
    },
    {
        "id": "/douga#touhou-3d-reimu-vs-yuyuko",
        "title": "[Touhou 3D] Reimu vs Yuyuko",
        "content": "[Touhou 3D] Reimu vs Yuyuko"
    },
    {
        "id": "/douga#touhou-3d-humans-vs-yukari",
        "title": "[Touhou 3D] Humans vs Yukari",
        "content": "[Touhou 3D] Humans vs Yukari"
    },
    {
        "id": "/douga#touhou-3d-subterranean-stars",
        "title": "[Touhou 3D] Subterranean Stars",
        "content": "[Touhou 3D] Subterranean Stars"
    },
    {
        "id": "/douga#touhou-3d-brambly-boundaries",
        "title": "[Touhou 3D] Brambly Boundaries",
        "content": "[Touhou 3D] Brambly Boundaries"
    },
    {
        "id": "/douga#touhou-3d-eternal-night---part-0",
        "title": "[Touhou 3D] Eternal Night - part 0",
        "content": "[Touhou 3D] Eternal Night - part 0"
    },
    {
        "id": "/douga#touhou-3d-eternal-night---part-1",
        "title": "[Touhou 3D] Eternal Night - part 1",
        "content": "[Touhou 3D] Eternal Night - part 1"
    },
    {
        "id": "/douga#搬运",
        "title": "搬运",
        "content": "搬运"
    },
    {
        "id": "/douga#3d东方灵梦-vs-蕾米莉亚-不用翻",
        "title": "【3D东方】灵梦 VS 蕾米莉亚不用翻",
        "content": "【3D东方】灵梦 VS 蕾米莉亚"
    },
    {
        "id": "/douga#3d东方魔理沙-vs-芙兰朵露-不用翻",
        "title": "【3D东方】魔理沙 VS 芙兰朵露不用翻",
        "content": "【3D东方】魔理沙 VS 芙兰朵露"
    },
    {
        "id": "/douga#3d东方灵梦-vs-幽幽子-不用翻",
        "title": "【3D东方】灵梦 VS 幽幽子不用翻",
        "content": "【3D东方】灵梦 VS 幽幽子"
    },
    {
        "id": "/douga#3d东方人类-vs-紫-不用翻",
        "title": "【3D东方】人类 VS 紫不用翻",
        "content": "【3D东方】人类 VS 紫"
    },
    {
        "id": "/douga#3d东方subterranean-stars-不用翻",
        "title": "【3D东方】Subterranean Stars不用翻",
        "content": "【3D东方】Subterranean Stars"
    },
    {
        "id": "/douga#3d东方subterranean-stars-不用翻-1",
        "title": "【3D东方】Subterranean Stars不用翻",
        "content": "【3D东方】Subterranean Stars"
    },
    {
        "id": "/douga#3d东方永夜抄---part-0-不用翻",
        "title": "【3D东方】永夜抄 - part 0不用翻",
        "content": "【3D东方】永夜抄 - part 0"
    },
    {
        "id": "/douga#3d东方永夜抄---part-1-不用翻",
        "title": "【3D东方】永夜抄 - part 1不用翻",
        "content": "【3D东方】永夜抄 - part 1"
    },
    {
        "id": "/douga#eternal-night",
        "title": "Eternal Night",
        "content": "Eternal Night"
    },
    {
        "id": "/douga#原视频-1",
        "title": "原视频",
        "content": "原视频"
    },
    {
        "id": "/douga#touhou-3d-eternal-night---part-0-1",
        "title": "[Touhou 3D] Eternal Night - part 0",
        "content": "[Touhou 3D] Eternal Night - part 0"
    },
    {
        "id": "/douga#touhou-3d-eternal-night---part-1-1",
        "title": "[Touhou 3D] Eternal Night - part 1",
        "content": "[Touhou 3D] Eternal Night - part 1"
    },
    {
        "id": "/douga#touhou-3d-eternal-night---part-2",
        "title": "[Touhou 3D] Eternal Night - part 2",
        "content": "[Touhou 3D] Eternal Night - part 2"
    },
    {
        "id": "/douga#搬运-1",
        "title": "搬运",
        "content": "搬运"
    },
    {
        "id": "/douga#3d东方永夜抄---part-0",
        "title": "【3D东方】永夜抄 - part 0",
        "content": "【3D东方】永夜抄 - part 0"
    },
    {
        "id": "/douga#3d东方永夜抄---part-1",
        "title": "【3D东方】永夜抄 - part 1",
        "content": "【3D东方】永夜抄 - part 1"
    },
    {
        "id": "/douga#3d东方永夜抄---part-2",
        "title": "【3D东方】永夜抄 - part 2",
        "content": "【3D东方】永夜抄 - part 2"
    }
]
